zengapay/__init__.py
zengapay/accounts.py
zengapay/client.py
zengapay/collection.py
zengapay/config.py
zengapay/errors.py
zengapay/transfer.py
zengapay/utils.py
zengapay-0.2.0.dist-info/LICENSE
zengapay-0.2.0.dist-info/METADATA
zengapay-0.2.0.dist-info/WHEEL
zengapay-0.2.0.dist-info/top_level.txt
zengapay-0.2.0.dist-info/RECORD
