Metadata-Version: 2.1
Name: zengapay
Version: 0.2.0
Summary: Python Wrapper for the ZengaPay API
Home-page: https://github.com/zengapay/zengapay-python
Author: Patrick Walukagga
Author-email: pwalukagga@gmail.com
License: MIT
Keywords: ZengaPay,ZengaPay API,ZengaPay Python Wrapper,ZengaPay Python
Platform: UNKNOWN
Classifier: Intended Audience :: Developers
Classifier: License :: OSI Approved :: MIT License
Classifier: Programming Language :: Python :: 3
Classifier: Programming Language :: Python :: 3.7
Classifier: Programming Language :: Python :: 3.8
Requires-Python: >=3.7.0
Requires-Dist: requests
Requires-Dist: phonenumbers
